imednet/AGENTS.md
imednet/__init__.py
imednet/airflow/__init__.py
imednet/async_sdk.py
imednet/auth/AGENTS.md
imednet/auth/__init__.py
imednet/cli/AGENTS.md
imednet/cli/__init__.py
imednet/cli/decorators.py
imednet/cli/export/__init__.py
imednet/cli/jobs/__init__.py
imednet/cli/queries/__init__.py
imednet/cli/record_revisions/__init__.py
imednet/cli/records/__init__.py
imednet/cli/sites/__init__.py
imednet/cli/studies/__init__.py
imednet/cli/subject_data.py
imednet/cli/subjects/__init__.py
imednet/cli/utils.py
imednet/cli/variables/__init__.py
imednet/cli/workflows/__init__.py
imednet/config.py
imednet/core/__init__.py
imednet/core/_requester.py
imednet/core/async_client.py
imednet/core/base_client.py
imednet/core/client.py
imednet/core/context.py
imednet/core/exceptions.py
imednet/core/http_client_base.py
imednet/core/paginator.py
imednet/core/retry.py
imednet/discovery.py
imednet/endpoints/__init__.py
imednet/endpoints/_mixins.py
imednet/endpoints/base.py
imednet/endpoints/codings.py
imednet/endpoints/forms.py
imednet/endpoints/intervals.py
imednet/endpoints/jobs.py
imednet/endpoints/queries.py
imednet/endpoints/record_revisions.py
imednet/endpoints/records.py
imednet/endpoints/sites.py
imednet/endpoints/studies.py
imednet/endpoints/subjects.py
imednet/endpoints/users.py
imednet/endpoints/variables.py
imednet/endpoints/visits.py
imednet/errors/AGENTS.md
imednet/errors/__init__.py
imednet/http/AGENTS.md
imednet/http/__init__.py
imednet/integrations/__init__.py
imednet/integrations/airflow/__init__.py
imednet/integrations/airflow/export.py
imednet/integrations/airflow/hooks/__init__.py
imednet/integrations/airflow/operators/__init__.py
imednet/integrations/airflow/operators/export.py
imednet/integrations/airflow/operators/to_s3.py
imednet/integrations/airflow/sensors.py
imednet/integrations/export.py
imednet/models/AGENTS.md
imednet/models/__init__.py
imednet/models/base.py
imednet/models/codings.py
imednet/models/forms.py
imednet/models/intervals.py
imednet-0.2.2.dist-info/METADATA
imednet-0.2.2.dist-info/WHEEL
imednet-0.2.2.dist-info/entry_points.txt
imednet-0.2.2.dist-info/licenses/LICENSE
imednet-0.2.2.dist-info/RECORD
