Metadata-Version: 2.4
Name: imednet
Version: 0.2.2
Summary: Unofficial Python SDK for the iMednet clinical trials API
License: MIT
License-File: LICENSE
Keywords: imednet,clinical trials,sdk,api
Author: Frederick de Ruiter
Author-email: 127706008+fderuiter@users.noreply.github.com
Maintainer: Frederick de Ruiter
Maintainer-email: fpderuiter@gmail.com
Requires-Python: >=3.10,<4.0
Classifier: Development Status :: 4 - Beta
Classifier: Intended Audience :: Developers
Classifier: Intended Audience :: Science/Research
Classifier: License :: OSI Approved :: MIT License
Classifier: Programming Language :: Python :: 3
Classifier: Programming Language :: Python :: 3.10
Classifier: Programming Language :: Python :: 3.11
Classifier: Programming Language :: Python :: 3.12
Classifier: Programming Language :: Python :: 3.13
Classifier: Programming Language :: Python :: 3.14
Classifier: Programming Language :: Python :: 3 :: Only
Classifier: Topic :: Scientific/Engineering :: Medical Science Apps.
Classifier: Typing :: Typed
Provides-Extra: airflow
Provides-Extra: excel
Provides-Extra: pandas
Provides-Extra: pyarrow
Provides-Extra: sqlalchemy
Requires-Dist: SQLAlchemy (>=2.0.0,<3.0.0) ; extra == "sqlalchemy"
Requires-Dist: h11 (==0.16.0)
Requires-Dist: httpx (>=0.28.1,<0.29.0)
Requires-Dist: openpyxl (>=3.1,<4.0) ; extra == "excel"
Requires-Dist: pandas (>=2.2.3,<3.0.0) ; extra == "pandas" or extra == "excel"
Requires-Dist: pyarrow (>=16.0.0,<17.0.0) ; extra == "pyarrow"
Requires-Dist: pydantic (>=2.11.3,<3.0.0)
Requires-Dist: python-dotenv (>=1.1.0,<2.0.0)
Requires-Dist: python-json-logger (>=2.0.7,<3.0.0)
Requires-Dist: requests (==2.32.4)
Requires-Dist: tenacity (>=9.1.2,<10.0.0)
Requires-Dist: typer[all] (>=0.15.2,<0.16.0)
Requires-Dist: urllib3 (>=2.6.0,<3.0.0)
Project-URL: Homepage, https://github.com/fderuiter/imednet-python-sdk
Project-URL: Repository, https://github.com/fderuiter/imednet-python-sdk
